strcase/__init__.py
strcase/strcase.py
strcase-1.0.0.dist-info/LICENSE
strcase-1.0.0.dist-info/METADATA
strcase-1.0.0.dist-info/WHEEL
strcase-1.0.0.dist-info/top_level.txt
strcase-1.0.0.dist-info/RECORD
