Metadata-Version: 2.1
Name: strcase
Version: 1.0.0
Summary: Convert string to specific case
Home-page: https://github.com/Fall1ngStar/strcase
Author: Fall1ngStar
License: UNKNOWN
Platform: UNKNOWN
Classifier: Programming Language :: Python :: 3
Classifier: License :: OSI Approved :: MIT License
Classifier: Operating System :: OS Independent
